custom_magics/__init__.py
custom_magics/custom_magics.py
custom_magics-0.0.7.dist-info/LICENSE
custom_magics-0.0.7.dist-info/METADATA
custom_magics-0.0.7.dist-info/WHEEL
custom_magics-0.0.7.dist-info/top_level.txt
custom_magics-0.0.7.dist-info/RECORD
