Metadata-Version: 2.1
Name: custom_magics
Version: 0.0.7
Summary: Custom Magic for Jupyter AI
Author: Mahesh Makwana
Author-email: maheshmakwana527@gmail.com
Keywords: python,jupyter,custom_magics,custom_function,openai
Classifier: Development Status :: 1 - Planning
Classifier: Intended Audience :: Developers
Classifier: Programming Language :: Python :: 3
Classifier: Operating System :: Unix
Classifier: Operating System :: MacOS :: MacOS X
Classifier: Operating System :: Microsoft :: Windows
License-File: LICENSE
Requires-Dist: jupyterlab
Requires-Dist: sphinx
Requires-Dist: python-dotenv
Requires-Dist: openai
